{"data":[{"author":{"avatar":{"url":"/assets/32x32_avatar.jpg"},"name":"Liam","slug":"nghenglim","tagline":"Make people great again!"},"banner":{"url":"/assets/2016010900.png"},"cover":{"url":"/assets/thumb-150-2016010900.png"},"description":"\n- many commits inside a feature branch\n- small enhancement or defect fix\n- not using git stash\n    ","postedAt":"2016-01-08T16:00:00.000Z","shortener":"4mOhTxZxK6NUvPI2YWBHwl","slug":"git-merging-or-combining-multiple-commits","title":"Git Merging or Combining Multiple Commits"}]}